helloworld.py
helloworld_package_2022-0.0.2.dist-info/LICENSE.txt
helloworld_package_2022-0.0.2.dist-info/METADATA
helloworld_package_2022-0.0.2.dist-info/WHEEL
helloworld_package_2022-0.0.2.dist-info/top_level.txt
helloworld_package_2022-0.0.2.dist-info/RECORD
