Metadata-Version: 2.1
Name: helloworld-package-2022
Version: 0.0.2
Summary: Say hello!
Author: zack588
Author-email: zakaribarj@yahoo.fr
License: UNKNOWN
Platform: UNKNOWN
License-File: LICENSE.txt
Requires-Dist: blessings (~=1.7)
Provides-Extra: dev
Requires-Dist: pytest (>=3.7) ; extra == 'dev'
Requires-Dist: tox ; extra == 'dev'
Requires-Dist: mkdocs (==1.1.2) ; extra == 'dev'
Requires-Dist: mkdocs-material (==7.1.5) ; extra == 'dev'
Requires-Dist: mkdocs-minify-plugin (==0.4.0) ; extra == 'dev'
Requires-Dist: mkdocs-git-revision-date-localized-plugin (==0.9.2) ; extra == 'dev'
Requires-Dist: mkdocs-git-authors-plugin (==0.3.3) ; extra == 'dev'
Requires-Dist: mkdocs-table-reader-plugin (==0.5) ; extra == 'dev'
Requires-Dist: mkdocs-img2fig-plugin (==0.9.3) ; extra == 'dev'
Requires-Dist: mknotebooks (==0.7.0) ; extra == 'dev'
Requires-Dist: mkdocs-awesome-pages-plugin (==2.5.0) ; extra == 'dev'
Requires-Dist: mkdocs-enumerate-headings-plugin (==0.4.4) ; extra == 'dev'
Requires-Dist: mkdocs-print-site-plugin (==1.2.3) ; extra == 'dev'
Requires-Dist: mkgendocs (==0.8.1) ; extra == 'dev'
